csortedintencode/__init__.py
csortedintencode/delta_varint_sortedint.cpython-311-x86_64-linux-gnu.so
csortedintencode-0.1.0.dist-info/LICENSE
csortedintencode-0.1.0.dist-info/METADATA
csortedintencode-0.1.0.dist-info/WHEEL
csortedintencode-0.1.0.dist-info/top_level.txt
csortedintencode-0.1.0.dist-info/RECORD
