Metadata-Version: 2.1
Name: csortedintencode
Version: 0.1.0
Summary: Efficient encoding and decoding of sorted lists of integers.
Home-page: https://github.com/davidlorenzana/csortedintencode
Author: David Lorenzana
Author-email: davlorenzana@gmail.com
License: MIT
Classifier: Programming Language :: Python :: 3
Classifier: License :: OSI Approved :: MIT License
Classifier: Topic :: Software Development :: Libraries :: Python Modules
Classifier: Topic :: System :: Archiving :: Compression
Classifier: Intended Audience :: Developers
Classifier: Operating System :: OS Independent
Requires-Python: >=3.7
License-File: LICENSE
